sqlalchemy_view_orm/__init__.py
sqlalchemy_view_orm/base.py
sqlalchemy_view_orm/py.typed
sqlalchemy_vieworm-0.1.1.dist-info/licenses/LICENSE
sqlalchemy_vieworm-0.1.1.dist-info/METADATA
sqlalchemy_vieworm-0.1.1.dist-info/WHEEL
sqlalchemy_vieworm-0.1.1.dist-info/top_level.txt
sqlalchemy_vieworm-0.1.1.dist-info/RECORD
