Metadata-Version: 2.4
Name: SQLAlchemy-ViewORM
Version: 0.1.1
Summary: A flexible ORM extension for defining and managing views (including materialized ones) in SQLAlchemy
Author-email: "AivanF." <fouren.aivan@gmail.com>
License: MIT License
Project-URL: Documentation, https://sqlalchemy-vieworm.readthedocs.io/
Project-URL: Repository, https://github.com/AivanF/SQLAlchemy-ViewORM
Project-URL: Bug Tracker, https://github.com/AivanF/SQLAlchemy-ViewORM/issues
Project-URL: Homepage, https://github.com/AivanF/SQLAlchemy-ViewORM
Project-URL: Source Code, https://github.com/AivanF/SQLAlchemy-ViewORM
Keywords: sqlalchemy,database,views,materialized views
Classifier: Development Status :: 4 - Beta
Classifier: Intended Audience :: Developers
Classifier: License :: OSI Approved :: MIT License
Classifier: Programming Language :: Python :: 3
Classifier: Programming Language :: Python :: 3.9
Classifier: Programming Language :: Python :: 3.10
Classifier: Programming Language :: Python :: 3.11
Classifier: Programming Language :: Python :: 3.12
Classifier: Topic :: Database
Classifier: Topic :: Software Development :: Libraries :: Python Modules
Classifier: Typing :: Typed
Requires-Python: >=3.9
License-File: LICENSE
Requires-Dist: sqlalchemy>=2.0.0
Provides-Extra: dev
Requires-Dist: pytest>=7.0.0; extra == "dev"
Requires-Dist: pytest-cov>=4.0.0; extra == "dev"
Requires-Dist: black>=23.0.0; extra == "dev"
Requires-Dist: isort>=5.0.0; extra == "dev"
Requires-Dist: mypy>=1.0.0; extra == "dev"
Requires-Dist: flake8>=6.0.0; extra == "dev"
Requires-Dist: pre-commit>=3.0.0; extra == "dev"
Requires-Dist: sphinx>=7.0.0; extra == "dev"
Requires-Dist: sphinx_rtd_theme>=1.3.0; extra == "dev"
Requires-Dist: build>=0.10.0; extra == "dev"
Requires-Dist: twine>=4.0.0; extra == "dev"
Provides-Extra: docs
Requires-Dist: sphinx>=7.0.0; extra == "docs"
Requires-Dist: sphinx_rtd_theme>=1.3.0; extra == "docs"
Provides-Extra: examples
Requires-Dist: fastapi>=0.95.0; extra == "examples"
Requires-Dist: uvicorn>=0.22.0; extra == "examples"
Dynamic: license-file
